package/__init__.py
package/module.py
mstturing-1.5.0.dist-info/LICENSE
mstturing-1.5.0.dist-info/METADATA
mstturing-1.5.0.dist-info/WHEEL
mstturing-1.5.0.dist-info/top_level.txt
mstturing-1.5.0.dist-info/RECORD
